Ozhabeme/__init__.py
Ozhabeme/statistics.py
ozhabeme-0.0.1.dist-info/licenses/LICENSE
ozhabeme-0.0.1.dist-info/METADATA
ozhabeme-0.0.1.dist-info/WHEEL
ozhabeme-0.0.1.dist-info/top_level.txt
ozhabeme-0.0.1.dist-info/RECORD
